pyezviz/__init__.py
pyezviz/__main__.py
pyezviz/api_endpoints.py
pyezviz/camera.py
pyezviz/cas.py
pyezviz/client.py
pyezviz/constants.py
pyezviz/exceptions.py
pyezviz/mqtt.py
pyezviz/test_cam_rtsp.py
pyezviz/utils.py
pyezviz_custom_batworkmode-0.2.2.3.dist-info/LICENSE.md
pyezviz_custom_batworkmode-0.2.2.3.dist-info/METADATA
pyezviz_custom_batworkmode-0.2.2.3.dist-info/WHEEL
pyezviz_custom_batworkmode-0.2.2.3.dist-info/entry_points.txt
pyezviz_custom_batworkmode-0.2.2.3.dist-info/top_level.txt
pyezviz_custom_batworkmode-0.2.2.3.dist-info/RECORD
